kedro_runners-0.1.1.dist-info/METADATA
kedro_runners-0.1.1.dist-info/WHEEL
kedro_runners/__init__.py
kedro_runners/runners/dry_runner.py
kedro_runners/runners/softfail_runner.py
kedro_runners-0.1.1.dist-info/RECORD
