Metadata-Version: 2.1
Name: kedro-runners
Version: 0.1.1
Summary: An extension of Kedro Runner
Author-Email: Nok Lam Chan <mediumnok@gmail.com>
License: Apache2
Requires-Python: >=3.9
Requires-Dist: kedro>=0.19.0
